{
  "type": "minecraft:crafting_shaped",
  "category": "misc",
  "pattern": [
    " 1 ",
    "345",
    " 7 "
  ],
  "key": {
    "1": {
      "item": "minecraft:acacia_planks"
    },
    "3": {
      "item": "minecraft:acacia_planks"
    },
    "4": {
      "item": "minecraft:orange_stained_glass"
    },
    "5": {
      "item": "minecraft:acacia_planks"
    },
    "7": {
      "item": "minecraft:acacia_planks"
    }
  },
  "result": {
    "item": "steel_and_more:orange_glass_with_in_acacia_frame",
    "count": 1
  }
}