{
  "_fv": 47,
  "_type": "recipe",
  "definition": {
    "recipeType": "Stone cutting",
    "recipeRetstackSize": 8,
    "group": "",
    "cookingBookCategory": "MISC",
    "xpReward": 0.0,
    "cookingTime": 200,
    "craftingBookCategory": "MISC",
    "recipeShapeless": false,
    "stoneCuttingInputStack": {
      "value": "Blocks.STRIPPED_SPRUCE_LOG"
    },
    "stoneCuttingReturnStack": {
      "value": "CUSTOM:VerticalSpruceSlab"
    },
    "name": "verticalspruceslabrecipe_6",
    "namespace": "mod"
  }
}